{
  "paging": { "pageIndex": 1, "pageSize": 100, "total": 152 },
  "baseComponent": {
    "id": "AYtaDl7-nPU9QxjXbOvP",
    "key": "fga-eps-mds_2023.2-UnB-TV-Frontend",
    "name": "2023.2-UnB-TV-Frontend",
    "qualifier": "TRK",
    "measures": [
      { "metric": "comment_lines_density", "value": "0.6", "bestValue": false },
      { "metric": "complexity", "value": "265" },
      { "metric": "coverage", "value": "93.7", "bestValue": false },
      {
        "metric": "duplicated_lines_density",
        "value": "0.0",
        "bestValue": true
      },
      { "metric": "files", "value": "90" },
      { "metric": "functions", "value": "187" },
      { "metric": "ncloc", "value": "2485" },
      { "metric": "security_rating", "value": "1.0", "bestValue": true }
    ]
  },
  "components": [
    {
      "id": "AYtaS0iUB6TD5Yb72jXW",
      "key": "fga-eps-mds_2023.2-UnB-TV-Frontend:src/app/pages/active-account",
      "name": "active-account",
      "qualifier": "DIR",
      "path": "src/app/pages/active-account",
      "measures": [
        {
          "metric": "comment_lines_density",
          "value": "0.0",
          "bestValue": false
        },
        { "metric": "complexity", "value": "13" },
        { "metric": "coverage", "value": "100.0", "bestValue": true },
        {
          "metric": "duplicated_lines_density",
          "value": "0.0",
          "bestValue": true
        },
        { "metric": "files", "value": "3" },
        { "metric": "functions", "value": "9" },
        { "metric": "ncloc", "value": "81" },
        { "metric": "security_rating", "value": "1.0", "bestValue": true }
      ]
    },
    {
      "id": "AYtaS0iUB6TD5Yb72jXU",
      "key": "fga-eps-mds_2023.2-UnB-TV-Frontend:src/app/pages/active-account/active-account.component.css",
      "name": "active-account.component.css",
      "qualifier": "FIL",
      "path": "src/app/pages/active-account/active-account.component.css",
      "language": "css",
      "measures": [
        { "metric": "files", "value": "1" },
        { "metric": "ncloc", "value": "0" },
        { "metric": "security_rating", "value": "1.0", "bestValue": true },
        {
          "metric": "duplicated_lines_density",
          "value": "0.0",
          "bestValue": true
        },
        { "metric": "test_failures", "value": "0", "bestValue": true },
        { "metric": "test_errors", "value": "0", "bestValue": true }
      ]
    },
    {
      "id": "AYtaS0iUB6TD5Yb72jXV",
      "key": "fga-eps-mds_2023.2-UnB-TV-Frontend:src/app/pages/active-account/active-account.component.html",
      "name": "active-account.component.html",
      "qualifier": "FIL",
      "path": "src/app/pages/active-account/active-account.component.html",
      "language": "web",
      "measures": [
        {
          "metric": "comment_lines_density",
          "value": "0.0",
          "bestValue": false
        },
        { "metric": "complexity", "value": "1" },
        { "metric": "files", "value": "1" },
        { "metric": "ncloc", "value": "14" },
        { "metric": "security_rating", "value": "1.0", "bestValue": true },
        {
          "metric": "duplicated_lines_density",
          "value": "0.0",
          "bestValue": true
        },
        { "metric": "test_failures", "value": "0", "bestValue": true },
        { "metric": "test_errors", "value": "0", "bestValue": true }
      ]
    },
    {
      "id": "AYtaS0iUB6TD5Yb72jXS",
      "key": "fga-eps-mds_2023.2-UnB-TV-Frontend:src/app/pages/active-account/active-account.component.spec.ts",
      "name": "active-account.component.spec.ts",
      "qualifier": "UTS",
      "path": "src/app/pages/active-account/active-account.component.spec.ts",
      "language": "ts",
      "measures": [
        { "metric": "security_rating", "value": "1.0", "bestValue": true },
        {
          "metric": "duplicated_lines_density",
          "value": "0.0",
          "bestValue": true
        },
        { "metric": "test_failures", "value": "0", "bestValue": true },
        { "metric": "test_errors", "value": "0", "bestValue": true }
      ]
    },
    {
      "id": "AYtaS0iUB6TD5Yb72jXT",
      "key": "fga-eps-mds_2023.2-UnB-TV-Frontend:src/app/pages/active-account/active-account.component.ts",
      "name": "active-account.component.ts",
      "qualifier": "FIL",
      "path": "src/app/pages/active-account/active-account.component.ts",
      "language": "ts",
      "measures": [
        {
          "metric": "comment_lines_density",
          "value": "0.0",
          "bestValue": false
        },
        { "metric": "complexity", "value": "12" },
        { "metric": "coverage", "value": "100.0", "bestValue": true },
        { "metric": "files", "value": "1" },
        { "metric": "functions", "value": "9" },
        { "metric": "ncloc", "value": "67" },
        { "metric": "security_rating", "value": "1.0", "bestValue": true },
        {
          "metric": "duplicated_lines_density",
          "value": "0.0",
          "bestValue": true
        },
        { "metric": "test_failures", "value": "0", "bestValue": true },
        { "metric": "test_errors", "value": "0", "bestValue": true }
      ]
    },
    {
      "id": "AYvss1WPTP9bVPDQQ89I",
      "key": "fga-eps-mds_2023.2-UnB-TV-Frontend:src/app/services/admin.guard.spec.ts",
      "name": "admin.guard.spec.ts",
      "qualifier": "UTS",
      "path": "src/app/services/admin.guard.spec.ts",
      "language": "ts",
      "measures": [
        { "metric": "security_rating", "value": "1.0", "bestValue": true },
        {
          "metric": "duplicated_lines_density",
          "value": "0.0",
          "bestValue": true
        },
        { "metric": "test_failures", "value": "0", "bestValue": true },
        { "metric": "test_errors", "value": "0", "bestValue": true }
      ]
    },
    {
      "id": "AYvss1WPTP9bVPDQQ89J",
      "key": "fga-eps-mds_2023.2-UnB-TV-Frontend:src/app/services/admin.guard.ts",
      "name": "admin.guard.ts",
      "qualifier": "FIL",
      "path": "src/app/services/admin.guard.ts",
      "language": "ts",
      "measures": [
        {
          "metric": "comment_lines_density",
          "value": "0.0",
          "bestValue": false
        },
        { "metric": "complexity", "value": "3" },
        { "metric": "coverage", "value": "100.0", "bestValue": true },
        { "metric": "files", "value": "1" },
        { "metric": "functions", "value": "2" },
        { "metric": "ncloc", "value": "21" },
        { "metric": "security_rating", "value": "1.0", "bestValue": true },
        {
          "metric": "duplicated_lines_density",
          "value": "0.0",
          "bestValue": true
        },
        { "metric": "test_failures", "value": "0", "bestValue": true },
        { "metric": "test_errors", "value": "0", "bestValue": true }
      ]
    },
    {
      "id": "AYvt46Php0h9nI6s-64_",
      "key": "fga-eps-mds_2023.2-UnB-TV-Frontend:src/app/pages/agora",
      "name": "agora",
      "qualifier": "DIR",
      "path": "src/app/pages/agora",
      "measures": [
        {
          "metric": "comment_lines_density",
          "value": "0.0",
          "bestValue": false
        },
        { "metric": "complexity", "value": "1" },
        { "metric": "coverage", "value": "100.0", "bestValue": true },
        {
          "metric": "duplicated_lines_density",
          "value": "0.0",
          "bestValue": true
        },
        { "metric": "files", "value": "3" },
        { "metric": "functions", "value": "0" },
        { "metric": "ncloc", "value": "9" },
        { "metric": "security_rating", "value": "1.0", "bestValue": true }
      ]
    },
    {
      "id": "AYvt46Php0h9nI6s-648",
      "key": "fga-eps-mds_2023.2-UnB-TV-Frontend:src/app/pages/agora/agora.component.css",
      "name": "agora.component.css",
      "qualifier": "FIL",
      "path": "src/app/pages/agora/agora.component.css",
      "language": "css",
      "measures": [
        { "metric": "files", "value": "1" },
        { "metric": "ncloc", "value": "0" },
        { "metric": "security_rating", "value": "1.0", "bestValue": true },
        {
          "metric": "duplicated_lines_density",
          "value": "0.0",
          "bestValue": true
        },
        { "metric": "test_failures", "value": "0", "bestValue": true },
        { "metric": "test_errors", "value": "0", "bestValue": true }
      ]
    },
    {
      "id": "AYvt46Php0h9nI6s-649",
      "key": "fga-eps-mds_2023.2-UnB-TV-Frontend:src/app/pages/agora/agora.component.html",
      "name": "agora.component.html",
      "qualifier": "FIL",
      "path": "src/app/pages/agora/agora.component.html",
      "language": "web",
      "measures": [
        {
          "metric": "comment_lines_density",
          "value": "0.0",
          "bestValue": false
        },
        { "metric": "complexity", "value": "1" },
        { "metric": "files", "value": "1" },
        { "metric": "ncloc", "value": "1" },
        { "metric": "security_rating", "value": "1.0", "bestValue": true },
        {
          "metric": "duplicated_lines_density",
          "value": "0.0",
          "bestValue": true
        },
        { "metric": "test_failures", "value": "0", "bestValue": true },
        { "metric": "test_errors", "value": "0", "bestValue": true }
      ]
    },
    {
      "id": "AYvt46Php0h9nI6s-64-",
      "key": "fga-eps-mds_2023.2-UnB-TV-Frontend:src/app/pages/agora/agora.component.spec.ts",
      "name": "agora.component.spec.ts",
      "qualifier": "UTS",
      "path": "src/app/pages/agora/agora.component.spec.ts",
      "language": "ts",
      "measures": [
        { "metric": "security_rating", "value": "1.0", "bestValue": true },
        {
          "metric": "duplicated_lines_density",
          "value": "0.0",
          "bestValue": true
        },
        { "metric": "test_failures", "value": "0", "bestValue": true },
        { "metric": "test_errors", "value": "0", "bestValue": true }
      ]
    },
    {
      "id": "AYvt46Php0h9nI6s-647",
      "key": "fga-eps-mds_2023.2-UnB-TV-Frontend:src/app/pages/agora/agora.component.ts",
      "name": "agora.component.ts",
      "qualifier": "FIL",
      "path": "src/app/pages/agora/agora.component.ts",
      "language": "ts",
      "measures": [
        {
          "metric": "comment_lines_density",
          "value": "0.0",
          "bestValue": false
        },
        { "metric": "complexity", "value": "0" },
        { "metric": "coverage", "value": "100.0", "bestValue": true },
        { "metric": "files", "value": "1" },
        { "metric": "functions", "value": "0" },
        { "metric": "ncloc", "value": "8" },
        { "metric": "security_rating", "value": "1.0", "bestValue": true },
        {
          "metric": "duplicated_lines_density",
          "value": "0.0",
          "bestValue": true
        },
        { "metric": "test_failures", "value": "0", "bestValue": true },
        { "metric": "test_errors", "value": "0", "bestValue": true }
      ]
    },
    {
      "id": "AYvaAQeNVO9wqyuIUadD",
      "key": "fga-eps-mds_2023.2-UnB-TV-Frontend:src/app/services/alert.service.spec.ts",
      "name": "alert.service.spec.ts",
      "qualifier": "UTS",
      "path": "src/app/services/alert.service.spec.ts",
      "language": "ts",
      "measures": [
        { "metric": "security_rating", "value": "1.0", "bestValue": true },
        {
          "metric": "duplicated_lines_density",
          "value": "0.0",
          "bestValue": true
        },
        { "metric": "test_failures", "value": "0", "bestValue": true },
        { "metric": "test_errors", "value": "0", "bestValue": true }
      ]
    },
    {
      "id": "AYvaAQeNVO9wqyuIUadE",
      "key": "fga-eps-mds_2023.2-UnB-TV-Frontend:src/app/services/alert.service.ts",
      "name": "alert.service.ts",
      "qualifier": "FIL",
      "path": "src/app/services/alert.service.ts",
      "language": "ts",
      "measures": [
        {
          "metric": "comment_lines_density",
          "value": "31.0",
          "bestValue": false
        },
        { "metric": "complexity", "value": "3" },
        { "metric": "coverage", "value": "100.0", "bestValue": true },
        { "metric": "files", "value": "1" },
        { "metric": "functions", "value": "3" },
        { "metric": "ncloc", "value": "20" },
        { "metric": "security_rating", "value": "1.0", "bestValue": true },
        {
          "metric": "duplicated_lines_density",
          "value": "0.0",
          "bestValue": true
        },
        { "metric": "test_failures", "value": "0", "bestValue": true },
        { "metric": "test_errors", "value": "0", "bestValue": true }
      ]
    },
    {
      "id": "AYtaEgoHx9_KfBlJtG-Z",
      "key": "fga-eps-mds_2023.2-UnB-TV-Frontend:src/app",
      "name": "app",
      "qualifier": "DIR",
      "path": "src/app",
      "measures": [
        {
          "metric": "comment_lines_density",
          "value": "0.6",
          "bestValue": false
        },
        { "metric": "complexity", "value": "255" },
        { "metric": "coverage", "value": "93.6", "bestValue": false },
        {
          "metric": "duplicated_lines_density",
          "value": "0.0",
          "bestValue": true
        },
        { "metric": "files", "value": "78" },
        { "metric": "functions", "value": "178" },
        { "metric": "ncloc", "value": "2337" },
        { "metric": "security_rating", "value": "1.0", "bestValue": true }
      ]
    },
    {
      "id": "AYtaEgoHx9_KfBlJtG-T",
      "key": "fga-eps-mds_2023.2-UnB-TV-Frontend:src/app/app-routing.module.ts",
      "name": "app-routing.module.ts",
      "qualifier": "FIL",
      "path": "src/app/app-routing.module.ts",
      "language": "ts",
      "measures": [
        {
          "metric": "comment_lines_density",
          "value": "1.9",
          "bestValue": false
        },
        { "metric": "complexity", "value": "0" },
        { "metric": "coverage", "value": "0.0", "bestValue": false },
        { "metric": "files", "value": "1" },
        { "metric": "functions", "value": "0" },
        { "metric": "ncloc", "value": "53" },
        { "metric": "security_rating", "value": "1.0", "bestValue": true },
        {
          "metric": "duplicated_lines_density",
          "value": "0.0",
          "bestValue": true
        },
        { "metric": "test_failures", "value": "0", "bestValue": true },
        { "metric": "test_errors", "value": "0", "bestValue": true }
      ]
    },
    {
      "id": "AYtaEgoHx9_KfBlJtG-U",
      "key": "fga-eps-mds_2023.2-UnB-TV-Frontend:src/app/app.component.css",
      "name": "app.component.css",
      "qualifier": "FIL",
      "path": "src/app/app.component.css",
      "language": "css",
      "measures": [
        { "metric": "files", "value": "1" },
        { "metric": "ncloc", "value": "0" },
        { "metric": "security_rating", "value": "1.0", "bestValue": true },
        {
          "metric": "duplicated_lines_density",
          "value": "0.0",
          "bestValue": true
        },
        { "metric": "test_failures", "value": "0", "bestValue": true },
        { "metric": "test_errors", "value": "0", "bestValue": true }
      ]
    },
    {
      "id": "AYtaEgoHx9_KfBlJtG-W",
      "key": "fga-eps-mds_2023.2-UnB-TV-Frontend:src/app/app.component.html",
      "name": "app.component.html",
      "qualifier": "FIL",
      "path": "src/app/app.component.html",
      "language": "web",
      "measures": [
        {
          "metric": "comment_lines_density",
          "value": "0.0",
          "bestValue": false
        },
        { "metric": "complexity", "value": "1" },
        { "metric": "files", "value": "1" },
        { "metric": "ncloc", "value": "5" },
        { "metric": "security_rating", "value": "1.0", "bestValue": true },
        {
          "metric": "duplicated_lines_density",
          "value": "0.0",
          "bestValue": true
        },
        { "metric": "test_failures", "value": "0", "bestValue": true },
        { "metric": "test_errors", "value": "0", "bestValue": true }
      ]
    },
    {
      "id": "AYtaEgoHx9_KfBlJtG-X",
      "key": "fga-eps-mds_2023.2-UnB-TV-Frontend:src/app/app.component.spec.ts",
      "name": "app.component.spec.ts",
      "qualifier": "UTS",
      "path": "src/app/app.component.spec.ts",
      "language": "ts",
      "measures": [
        { "metric": "security_rating", "value": "1.0", "bestValue": true },
        {
          "metric": "duplicated_lines_density",
          "value": "0.0",
          "bestValue": true
        },
        { "metric": "test_failures", "value": "0", "bestValue": true },
        { "metric": "test_errors", "value": "0", "bestValue": true }
      ]
    },
    {
      "id": "AYtaEgoHx9_KfBlJtG-Y",
      "key": "fga-eps-mds_2023.2-UnB-TV-Frontend:src/app/app.component.ts",
      "name": "app.component.ts",
      "qualifier": "FIL",
      "path": "src/app/app.component.ts",
      "language": "ts",
      "measures": [
        {
          "metric": "comment_lines_density",
          "value": "0.0",
          "bestValue": false
        },
        { "metric": "complexity", "value": "0" },
        { "metric": "coverage", "value": "100.0", "bestValue": true },
        { "metric": "files", "value": "1" },
        { "metric": "functions", "value": "0" },
        { "metric": "ncloc", "value": "9" },
        { "metric": "security_rating", "value": "1.0", "bestValue": true },
        {
          "metric": "duplicated_lines_density",
          "value": "0.0",
          "bestValue": true
        },
        { "metric": "test_failures", "value": "0", "bestValue": true },
        { "metric": "test_errors", "value": "0", "bestValue": true }
      ]
    },
    {
      "id": "AYtaEgoHx9_KfBlJtG-V",
      "key": "fga-eps-mds_2023.2-UnB-TV-Frontend:src/app/app.module.ts",
      "name": "app.module.ts",
      "qualifier": "FIL",
      "path": "src/app/app.module.ts",
      "language": "ts",
      "measures": [
        {
          "metric": "comment_lines_density",
          "value": "1.1",
          "bestValue": false
        },
        { "metric": "complexity", "value": "0" },
        { "metric": "files", "value": "1" },
        { "metric": "functions", "value": "0" },
        { "metric": "ncloc", "value": "92" },
        { "metric": "security_rating", "value": "1.0", "bestValue": true },
        {
          "metric": "duplicated_lines_density",
          "value": "0.0",
          "bestValue": true
        },
        { "metric": "test_failures", "value": "0", "bestValue": true },
        { "metric": "test_errors", "value": "0", "bestValue": true }
      ]
    },
    {
      "id": "AYvaCKRBZUStRRCQ-ygW",
      "key": "fga-eps-mds_2023.2-UnB-TV-Frontend:src/app/guard/auth.guard.spec.ts",
      "name": "auth.guard.spec.ts",
      "qualifier": "UTS",
      "path": "src/app/guard/auth.guard.spec.ts",
      "language": "ts",
      "measures": [
        { "metric": "security_rating", "value": "1.0", "bestValue": true },
        {
          "metric": "duplicated_lines_density",
          "value": "0.0",
          "bestValue": true
        },
        { "metric": "test_failures", "value": "0", "bestValue": true },
        { "metric": "test_errors", "value": "0", "bestValue": true }
      ]
    },
    {
      "id": "AYvaCKRBZUStRRCQ-ygY",
      "key": "fga-eps-mds_2023.2-UnB-TV-Frontend:src/app/guard/auth.guard.ts",
      "name": "auth.guard.ts",
      "qualifier": "FIL",
      "path": "src/app/guard/auth.guard.ts",
      "language": "ts",
      "measures": [
        {
          "metric": "comment_lines_density",
          "value": "0.0",
          "bestValue": false
        },
        { "metric": "complexity", "value": "3" },
        { "metric": "coverage", "value": "100.0", "bestValue": true },
        { "metric": "files", "value": "1" },
        { "metric": "functions", "value": "2" },
        { "metric": "ncloc", "value": "17" },
        { "metric": "security_rating", "value": "1.0", "bestValue": true },
        {
          "metric": "duplicated_lines_density",
          "value": "0.0",
          "bestValue": true
        },
        { "metric": "test_failures", "value": "0", "bestValue": true },
        { "metric": "test_errors", "value": "0", "bestValue": true }
      ]
    },
    {
      "id": "AYtaS0iUB6TD5Yb72jWz",
      "key": "fga-eps-mds_2023.2-UnB-TV-Frontend:src/app/services/auth.service.spec.ts",
      "name": "auth.service.spec.ts",
      "qualifier": "UTS",
      "path": "src/app/services/auth.service.spec.ts",
      "language": "ts",
      "measures": [
        { "metric": "security_rating", "value": "1.0", "bestValue": true },
        {
          "metric": "duplicated_lines_density",
          "value": "0.0",
          "bestValue": true
        },
        { "metric": "test_failures", "value": "0", "bestValue": true },
        { "metric": "test_errors", "value": "0", "bestValue": true }
      ]
    },
    {
      "id": "AYtaS0iUB6TD5Yb72jWy",
      "key": "fga-eps-mds_2023.2-UnB-TV-Frontend:src/app/services/auth.service.ts",
      "name": "auth.service.ts",
      "qualifier": "FIL",
      "path": "src/app/services/auth.service.ts",
      "language": "ts",
      "measures": [
        {
          "metric": "comment_lines_density",
          "value": "0.0",
          "bestValue": false
        },
        { "metric": "complexity", "value": "10" },
        { "metric": "coverage", "value": "100.0", "bestValue": true },
        { "metric": "files", "value": "1" },
        { "metric": "functions", "value": "10" },
        { "metric": "ncloc", "value": "41" },
        { "metric": "security_rating", "value": "1.0", "bestValue": true },
        {
          "metric": "duplicated_lines_density",
          "value": "0.0",
          "bestValue": true
        },
        { "metric": "test_failures", "value": "0", "bestValue": true },
        { "metric": "test_errors", "value": "0", "bestValue": true }
      ]
    },
    {
      "id": "AYtaS0iUB6TD5Yb72jXb",
      "key": "fga-eps-mds_2023.2-UnB-TV-Frontend:src/app/components/background",
      "name": "background",
      "qualifier": "DIR",
      "path": "src/app/components/background",
      "measures": [
        {
          "metric": "comment_lines_density",
          "value": "0.7",
          "bestValue": false
        },
        { "metric": "complexity", "value": "10" },
        { "metric": "coverage", "value": "100.0", "bestValue": true },
        {
          "metric": "duplicated_lines_density",
          "value": "0.0",
          "bestValue": true
        },
        { "metric": "files", "value": "3" },
        { "metric": "functions", "value": "3" },
        { "metric": "ncloc", "value": "151" },
        { "metric": "security_rating", "value": "1.0", "bestValue": true }
      ]
    },
    {
      "id": "AYtaS0iUB6TD5Yb72jXa",
      "key": "fga-eps-mds_2023.2-UnB-TV-Frontend:src/app/components/background/background.component.css",
      "name": "background.component.css",
      "qualifier": "FIL",
      "path": "src/app/components/background/background.component.css",
      "language": "css",
      "measures": [
        {
          "metric": "comment_lines_density",
          "value": "0.0",
          "bestValue": false
        },
        { "metric": "files", "value": "1" },
        { "metric": "ncloc", "value": "13" },
        { "metric": "security_rating", "value": "1.0", "bestValue": true },
        {
          "metric": "duplicated_lines_density",
          "value": "0.0",
          "bestValue": true
        },
        { "metric": "test_failures", "value": "0", "bestValue": true },
        { "metric": "test_errors", "value": "0", "bestValue": true }
      ]
    },
    {
      "id": "AYtaS0iUB6TD5Yb72jXY",
      "key": "fga-eps-mds_2023.2-UnB-TV-Frontend:src/app/components/background/background.component.html",
      "name": "background.component.html",
      "qualifier": "FIL",
      "path": "src/app/components/background/background.component.html",
      "language": "web",
      "measures": [
        {
          "metric": "comment_lines_density",
          "value": "0.0",
          "bestValue": false
        },
        { "metric": "complexity", "value": "1" },
        { "metric": "files", "value": "1" },
        { "metric": "ncloc", "value": "102" },
        { "metric": "security_rating", "value": "1.0", "bestValue": true },
        {
          "metric": "duplicated_lines_density",
          "value": "0.0",
          "bestValue": true
        },
        { "metric": "test_failures", "value": "0", "bestValue": true },
        { "metric": "test_errors", "value": "0", "bestValue": true }
      ]
    },
    {
      "id": "AYtaS0iUB6TD5Yb72jXX",
      "key": "fga-eps-mds_2023.2-UnB-TV-Frontend:src/app/components/background/background.component.spec.ts",
      "name": "background.component.spec.ts",
      "qualifier": "UTS",
      "path": "src/app/components/background/background.component.spec.ts",
      "language": "ts",
      "measures": [
        { "metric": "security_rating", "value": "1.0", "bestValue": true },
        {
          "metric": "duplicated_lines_density",
          "value": "0.0",
          "bestValue": true
        },
        { "metric": "test_failures", "value": "0", "bestValue": true },
        { "metric": "test_errors", "value": "0", "bestValue": true }
      ]
    },
    {
      "id": "AYtaS0iUB6TD5Yb72jXZ",
      "key": "fga-eps-mds_2023.2-UnB-TV-Frontend:src/app/components/background/background.component.ts",
      "name": "background.component.ts",
      "qualifier": "FIL",
      "path": "src/app/components/background/background.component.ts",
      "language": "ts",
      "measures": [
        {
          "metric": "comment_lines_density",
          "value": "2.7",
          "bestValue": false
        },
        { "metric": "complexity", "value": "9" },
        { "metric": "coverage", "value": "100.0", "bestValue": true },
        { "metric": "files", "value": "1" },
        { "metric": "functions", "value": "3" },
        { "metric": "ncloc", "value": "36" },
        { "metric": "security_rating", "value": "1.0", "bestValue": true },
        {
          "metric": "duplicated_lines_density",
          "value": "0.0",
          "bestValue": true
        },
        { "metric": "test_failures", "value": "0", "bestValue": true },
        { "metric": "test_errors", "value": "0", "bestValue": true }
      ]
    },
    {
      "id": "AYtaS0iUB6TD5Yb72jXM",
      "key": "fga-eps-mds_2023.2-UnB-TV-Frontend:src/app/pages/check-code-rest-password",
      "name": "check-code-rest-password",
      "qualifier": "DIR",
      "path": "src/app/pages/check-code-rest-password",
      "measures": [
        {
          "metric": "comment_lines_density",
          "value": "0.0",
          "bestValue": false
        },
        { "metric": "complexity", "value": "12" },
        { "metric": "coverage", "value": "100.0", "bestValue": true },
        {
          "metric": "duplicated_lines_density",
          "value": "0.0",
          "bestValue": true
        },
        { "metric": "files", "value": "3" },
        { "metric": "functions", "value": "9" },
        { "metric": "ncloc", "value": "104" },
        { "metric": "security_rating", "value": "1.0", "bestValue": true }
      ]
    },
    {
      "id": "AYtaS0iUB6TD5Yb72jXI",
      "key": "fga-eps-mds_2023.2-UnB-TV-Frontend:src/app/pages/check-code-rest-password/check-code-rest-password.component.css",
      "name": "check-code-rest-password.component.css",
      "qualifier": "FIL",
      "path": "src/app/pages/check-code-rest-password/check-code-rest-password.component.css",
      "language": "css",
      "measures": [
        { "metric": "files", "value": "1" },
        { "metric": "ncloc", "value": "0" },
        { "metric": "security_rating", "value": "1.0", "bestValue": true },
        {
          "metric": "duplicated_lines_density",
          "value": "0.0",
          "bestValue": true
        },
        { "metric": "test_failures", "value": "0", "bestValue": true },
        { "metric": "test_errors", "value": "0", "bestValue": true }
      ]
    },
    {
      "id": "AYtaS0iUB6TD5Yb72jXK",
      "key": "fga-eps-mds_2023.2-UnB-TV-Frontend:src/app/pages/check-code-rest-password/check-code-rest-password.component.html",
      "name": "check-code-rest-password.component.html",
      "qualifier": "FIL",
      "path": "src/app/pages/check-code-rest-password/check-code-rest-password.component.html",
      "language": "web",
      "measures": [
        {
          "metric": "comment_lines_density",
          "value": "0.0",
          "bestValue": false
        },
        { "metric": "complexity", "value": "1" },
        { "metric": "files", "value": "1" },
        { "metric": "ncloc", "value": "42" },
        { "metric": "security_rating", "value": "1.0", "bestValue": true },
        {
          "metric": "duplicated_lines_density",
          "value": "0.0",
          "bestValue": true
        },
        { "metric": "test_failures", "value": "0", "bestValue": true },
        { "metric": "test_errors", "value": "0", "bestValue": true }
      ]
    },
    {
      "id": "AYtaS0iUB6TD5Yb72jXJ",
      "key": "fga-eps-mds_2023.2-UnB-TV-Frontend:src/app/pages/check-code-rest-password/check-code-rest-password.component.spec.ts",
      "name": "check-code-rest-password.component.spec.ts",
      "qualifier": "UTS",
      "path": "src/app/pages/check-code-rest-password/check-code-rest-password.component.spec.ts",
      "language": "ts",
      "measures": [
        { "metric": "security_rating", "value": "1.0", "bestValue": true },
        {
          "metric": "duplicated_lines_density",
          "value": "0.0",
          "bestValue": true
        },
        { "metric": "test_failures", "value": "0", "bestValue": true },
        { "metric": "test_errors", "value": "0", "bestValue": true }
      ]
    },
    {
      "id": "AYtaS0iUB6TD5Yb72jXL",
      "key": "fga-eps-mds_2023.2-UnB-TV-Frontend:src/app/pages/check-code-rest-password/check-code-rest-password.component.ts",
      "name": "check-code-rest-password.component.ts",
      "qualifier": "FIL",
      "path": "src/app/pages/check-code-rest-password/check-code-rest-password.component.ts",
      "language": "ts",
      "measures": [
        {
          "metric": "comment_lines_density",
          "value": "0.0",
          "bestValue": false
        },
        { "metric": "complexity", "value": "11" },
        { "metric": "coverage", "value": "100.0", "bestValue": true },
        { "metric": "files", "value": "1" },
        { "metric": "functions", "value": "9" },
        { "metric": "ncloc", "value": "62" },
        { "metric": "security_rating", "value": "1.0", "bestValue": true },
        {
          "metric": "duplicated_lines_density",
          "value": "0.0",
          "bestValue": true
        },
        { "metric": "test_failures", "value": "0", "bestValue": true },
        { "metric": "test_errors", "value": "0", "bestValue": true }
      ]
    },
    {
      "id": "AYvZ8QU8UTZAVxbJFIaC",
      "key": "fga-eps-mds_2023.2-UnB-TV-Frontend:src/shared/model/comment.model.ts",
      "name": "comment.model.ts",
      "qualifier": "FIL",
      "path": "src/shared/model/comment.model.ts",
      "language": "ts",
      "measures": [
        {
          "metric": "comment_lines_density",
          "value": "0.0",
          "bestValue": false
        },
        { "metric": "complexity", "value": "1" },
        { "metric": "files", "value": "1" },
        { "metric": "functions", "value": "1" },
        { "metric": "ncloc", "value": "18" },
        { "metric": "security_rating", "value": "1.0", "bestValue": true },
        {
          "metric": "duplicated_lines_density",
          "value": "0.0",
          "bestValue": true
        },
        { "metric": "test_failures", "value": "0", "bestValue": true },
        { "metric": "test_errors", "value": "0", "bestValue": true }
      ]
    },
    {
      "id": "AYvZ8QU8UTZAVxbJFIaB",
      "key": "fga-eps-mds_2023.2-UnB-TV-Frontend:src/app/components",
      "name": "components",
      "qualifier": "DIR",
      "path": "src/app/components",
      "measures": [
        {
          "metric": "comment_lines_density",
          "value": "0.6",
          "bestValue": false
        },
        { "metric": "complexity", "value": "28" },
        { "metric": "coverage", "value": "100.0", "bestValue": true },
        {
          "metric": "duplicated_lines_density",
          "value": "0.0",
          "bestValue": true
        },
        { "metric": "files", "value": "6" },
        { "metric": "functions", "value": "16" },
        { "metric": "ncloc", "value": "314" },
        { "metric": "security_rating", "value": "1.0", "bestValue": true }
      ]
    },
    {
      "id": "AYwiW-w7MpD-XHVyYc1i",
      "key": "fga-eps-mds_2023.2-UnB-TV-Frontend:src/app/services/date.service.spec.ts",
      "name": "date.service.spec.ts",
      "qualifier": "UTS",
      "path": "src/app/services/date.service.spec.ts",
      "language": "ts",
      "measures": [
        { "metric": "security_rating", "value": "1.0", "bestValue": true },
        {
          "metric": "duplicated_lines_density",
          "value": "0.0",
          "bestValue": true
        },
        { "metric": "test_failures", "value": "0", "bestValue": true },
        { "metric": "test_errors", "value": "0", "bestValue": true }
      ]
    },
    {
      "id": "AYwiW-w7MpD-XHVyYc1h",
      "key": "fga-eps-mds_2023.2-UnB-TV-Frontend:src/app/services/date.service.ts",
      "name": "date.service.ts",
      "qualifier": "FIL",
      "path": "src/app/services/date.service.ts",
      "language": "ts",
      "measures": [
        {
          "metric": "comment_lines_density",
          "value": "3.7",
          "bestValue": false
        },
        { "metric": "complexity", "value": "5" },
        { "metric": "coverage", "value": "100.0", "bestValue": true },
        { "metric": "files", "value": "1" },
        { "metric": "functions", "value": "4" },
        { "metric": "ncloc", "value": "26" },
        { "metric": "security_rating", "value": "1.0", "bestValue": true },
        {
          "metric": "duplicated_lines_density",
          "value": "0.0",
          "bestValue": true
        },
        { "metric": "test_failures", "value": "0", "bestValue": true },
        { "metric": "test_errors", "value": "0", "bestValue": true }
      ]
    },
    {
      "id": "AYtaS0iUB6TD5Yb72jXR",
      "key": "fga-eps-mds_2023.2-UnB-TV-Frontend:src/app/pages/edit-user",
      "name": "edit-user",
      "qualifier": "DIR",
      "path": "src/app/pages/edit-user",
      "measures": [
        {
          "metric": "comment_lines_density",
          "value": "0.0",
          "bestValue": false
        },
        { "metric": "complexity", "value": "23" },
        { "metric": "coverage", "value": "88.2", "bestValue": false },
        {
          "metric": "duplicated_lines_density",
          "value": "0.0",
          "bestValue": true
        },
        { "metric": "files", "value": "3" },
        { "metric": "functions", "value": "14" },
        { "metric": "ncloc", "value": "125" },
        { "metric": "security_rating", "value": "1.0", "bestValue": true }
      ]
    },
    {
      "id": "AYtaS0iUB6TD5Yb72jXO",
      "key": "fga-eps-mds_2023.2-UnB-TV-Frontend:src/app/pages/edit-user/edit-user.component.css",
      "name": "edit-user.component.css",
      "qualifier": "FIL",
      "path": "src/app/pages/edit-user/edit-user.component.css",
      "language": "css",
      "measures": [
        { "metric": "files", "value": "1" },
        { "metric": "ncloc", "value": "0" },
        { "metric": "security_rating", "value": "1.0", "bestValue": true },
        {
          "metric": "duplicated_lines_density",
          "value": "0.0",
          "bestValue": true
        },
        { "metric": "test_failures", "value": "0", "bestValue": true },
        { "metric": "test_errors", "value": "0", "bestValue": true }
      ]
    },
    {
      "id": "AYtaS0iUB6TD5Yb72jXQ",
      "key": "fga-eps-mds_2023.2-UnB-TV-Frontend:src/app/pages/edit-user/edit-user.component.html",
      "name": "edit-user.component.html",
      "qualifier": "FIL",
      "path": "src/app/pages/edit-user/edit-user.component.html",
      "language": "web",
      "measures": [
        {
          "metric": "comment_lines_density",
          "value": "0.0",
          "bestValue": false
        },
        { "metric": "complexity", "value": "1" },
        { "metric": "files", "value": "1" },
        { "metric": "ncloc", "value": "18" },
        { "metric": "security_rating", "value": "1.0", "bestValue": true },
        {
          "metric": "duplicated_lines_density",
          "value": "0.0",
          "bestValue": true
        },
        { "metric": "test_failures", "value": "0", "bestValue": true },
        { "metric": "test_errors", "value": "0", "bestValue": true }
      ]
    },
    {
      "id": "AYtaS0iUB6TD5Yb72jXP",
      "key": "fga-eps-mds_2023.2-UnB-TV-Frontend:src/app/pages/edit-user/edit-user.component.spec.ts",
      "name": "edit-user.component.spec.ts",
      "qualifier": "UTS",
      "path": "src/app/pages/edit-user/edit-user.component.spec.ts",
      "language": "ts",
      "measures": [
        { "metric": "security_rating", "value": "1.0", "bestValue": true },
        {
          "metric": "duplicated_lines_density",
          "value": "0.0",
          "bestValue": true
        },
        { "metric": "test_failures", "value": "0", "bestValue": true },
        { "metric": "test_errors", "value": "0", "bestValue": true }
      ]
    },
    {
      "id": "AYtaS0iUB6TD5Yb72jXN",
      "key": "fga-eps-mds_2023.2-UnB-TV-Frontend:src/app/pages/edit-user/edit-user.component.ts",
      "name": "edit-user.component.ts",
      "qualifier": "FIL",
      "path": "src/app/pages/edit-user/edit-user.component.ts",
      "language": "ts",
      "measures": [
        {
          "metric": "comment_lines_density",
          "value": "0.0",
          "bestValue": false
        },
        { "metric": "complexity", "value": "22" },
        { "metric": "coverage", "value": "88.2", "bestValue": false },
        { "metric": "files", "value": "1" },
        { "metric": "functions", "value": "14" },
        { "metric": "ncloc", "value": "107" },
        { "metric": "security_rating", "value": "1.0", "bestValue": true },
        {
          "metric": "duplicated_lines_density",
          "value": "0.0",
          "bestValue": true
        },
        { "metric": "test_failures", "value": "0", "bestValue": true },
        { "metric": "test_errors", "value": "0", "bestValue": true }
      ]
    },
    {
      "id": "AYtaa6xNgKV0OlXg3jpM",
      "key": "fga-eps-mds_2023.2-UnB-TV-Frontend:src/shared/model/eduplay-by-institution.model.ts",
      "name": "eduplay-by-institution.model.ts",
      "qualifier": "FIL",
      "path": "src/shared/model/eduplay-by-institution.model.ts",
      "language": "ts",
      "measures": [
        {
          "metric": "comment_lines_density",
          "value": "0.0",
          "bestValue": false
        },
        { "metric": "complexity", "value": "1" },
        { "metric": "files", "value": "1" },
        { "metric": "functions", "value": "1" },
        { "metric": "ncloc", "value": "9" },
        { "metric": "security_rating", "value": "1.0", "bestValue": true },
        {
          "metric": "duplicated_lines_density",
          "value": "0.0",
          "bestValue": true
        },
        { "metric": "test_failures", "value": "0", "bestValue": true },
        { "metric": "test_errors", "value": "0", "bestValue": true }
      ]
    },
    {
      "id": "AYvOSGImPdOXal5RwOsg",
      "key": "fga-eps-mds_2023.2-UnB-TV-Frontend:src/shared/model/email.model.ts",
      "name": "email.model.ts",
      "qualifier": "FIL",
      "path": "src/shared/model/email.model.ts",
      "language": "ts",
      "measures": [
        {
          "metric": "comment_lines_density",
          "value": "0.0",
          "bestValue": false
        },
        { "metric": "complexity", "value": "1" },
        { "metric": "coverage", "value": "100.0", "bestValue": true },
        { "metric": "files", "value": "1" },
        { "metric": "functions", "value": "1" },
        { "metric": "ncloc", "value": "22" },
        { "metric": "security_rating", "value": "1.0", "bestValue": true },
        {
          "metric": "duplicated_lines_density",
          "value": "0.0",
          "bestValue": true
        },
        { "metric": "test_failures", "value": "0", "bestValue": true },
        { "metric": "test_errors", "value": "0", "bestValue": true }
      ]
    },
    {
      "id": "AYvOSGImPdOXal5RwOse",
      "key": "fga-eps-mds_2023.2-UnB-TV-Frontend:src/app/services/email.service.spec.ts",
      "name": "email.service.spec.ts",
      "qualifier": "UTS",
      "path": "src/app/services/email.service.spec.ts",
      "language": "ts",
      "measures": [
        { "metric": "security_rating", "value": "1.0", "bestValue": true },
        {
          "metric": "duplicated_lines_density",
          "value": "0.0",
          "bestValue": true
        },
        { "metric": "test_failures", "value": "0", "bestValue": true },
        { "metric": "test_errors", "value": "0", "bestValue": true }
      ]
    },
    {
      "id": "AYvOSGImPdOXal5RwOsf",
      "key": "fga-eps-mds_2023.2-UnB-TV-Frontend:src/app/services/email.service.ts",
      "name": "email.service.ts",
      "qualifier": "FIL",
      "path": "src/app/services/email.service.ts",
      "language": "ts",
      "measures": [
        {
          "metric": "comment_lines_density",
          "value": "6.3",
          "bestValue": false
        },
        { "metric": "complexity", "value": "2" },
        { "metric": "coverage", "value": "100.0", "bestValue": true },
        { "metric": "files", "value": "1" },
        { "metric": "functions", "value": "2" },
        { "metric": "ncloc", "value": "15" },
        { "metric": "security_rating", "value": "1.0", "bestValue": true },
        {
          "metric": "duplicated_lines_density",
          "value": "0.0",
          "bestValue": true
        },
        { "metric": "test_failures", "value": "0", "bestValue": true },
        { "metric": "test_errors", "value": "0", "bestValue": true }
      ]
    },
    {
      "id": "AYvsukM1bFJvH7dUSIYC",
      "key": "fga-eps-mds_2023.2-UnB-TV-Frontend:src/app/pages/grid",
      "name": "grid",
      "qualifier": "DIR",
      "path": "src/app/pages/grid",
      "measures": [
        {
          "metric": "comment_lines_density",
          "value": "0.0",
          "bestValue": false
        },
        { "metric": "complexity", "value": "7" },
        { "metric": "coverage", "value": "100.0", "bestValue": true },
        {
          "metric": "duplicated_lines_density",
          "value": "0.0",
          "bestValue": true
        },
        { "metric": "files", "value": "3" },
        { "metric": "functions", "value": "6" },
        { "metric": "ncloc", "value": "91" },
        { "metric": "security_rating", "value": "1.0", "bestValue": true }
      ]
    },
    {
      "id": "AYvsukM1bFJvH7dUSIYH",
      "key": "fga-eps-mds_2023.2-UnB-TV-Frontend:src/app/pages/grid-days",
      "name": "grid-days",
      "qualifier": "DIR",
      "path": "src/app/pages/grid-days",
      "measures": [
        {
          "metric": "comment_lines_density",
          "value": "0.0",
          "bestValue": false
        },
        { "metric": "complexity", "value": "3" },
        { "metric": "coverage", "value": "100.0", "bestValue": true },
        {
          "metric": "duplicated_lines_density",
          "value": "0.0",
          "bestValue": true
        },
        { "metric": "files", "value": "3" },
        { "metric": "functions", "value": "2" },
        { "metric": "ncloc", "value": "27" },
        { "metric": "security_rating", "value": "1.0", "bestValue": true }
      ]
    },
    {
      "id": "AYvsukM1bFJvH7dUSIYG",
      "key": "fga-eps-mds_2023.2-UnB-TV-Frontend:src/app/pages/grid-days/grid-days.component.css",
      "name": "grid-days.component.css",
      "qualifier": "FIL",
      "path": "src/app/pages/grid-days/grid-days.component.css",
      "language": "css",
      "measures": [
        {
          "metric": "comment_lines_density",
          "value": "0.0",
          "bestValue": false
        },
        { "metric": "files", "value": "1" },
        { "metric": "ncloc", "value": "6" },
        { "metric": "security_rating", "value": "1.0", "bestValue": true },
        {
          "metric": "duplicated_lines_density",
          "value": "0.0",
          "bestValue": true
        },
        { "metric": "test_failures", "value": "0", "bestValue": true },
        { "metric": "test_errors", "value": "0", "bestValue": true }
      ]
    },
    {
      "id": "AYvsukM1bFJvH7dUSIYF",
      "key": "fga-eps-mds_2023.2-UnB-TV-Frontend:src/app/pages/grid-days/grid-days.component.html",
      "name": "grid-days.component.html",
      "qualifier": "FIL",
      "path": "src/app/pages/grid-days/grid-days.component.html",
      "language": "web",
      "measures": [
        {
          "metric": "comment_lines_density",
          "value": "0.0",
          "bestValue": false
        },
        { "metric": "complexity", "value": "1" },
        { "metric": "files", "value": "1" },
        { "metric": "ncloc", "value": "5" },
        { "metric": "security_rating", "value": "1.0", "bestValue": true },
        {
          "metric": "duplicated_lines_density",
          "value": "0.0",
          "bestValue": true
        },
        { "metric": "test_failures", "value": "0", "bestValue": true },
        { "metric": "test_errors", "value": "0", "bestValue": true }
      ]
    },
    {
      "id": "AYvsukM1bFJvH7dUSIYE",
      "key": "fga-eps-mds_2023.2-UnB-TV-Frontend:src/app/pages/grid-days/grid-days.component.spec.ts",
      "name": "grid-days.component.spec.ts",
      "qualifier": "UTS",
      "path": "src/app/pages/grid-days/grid-days.component.spec.ts",
      "language": "ts",
      "measures": [
        { "metric": "security_rating", "value": "1.0", "bestValue": true },
        {
          "metric": "duplicated_lines_density",
          "value": "0.0",
          "bestValue": true
        },
        { "metric": "test_failures", "value": "0", "bestValue": true },
        { "metric": "test_errors", "value": "0", "bestValue": true }
      ]
    },
    {
      "id": "AYvsukM1bFJvH7dUSIYD",
      "key": "fga-eps-mds_2023.2-UnB-TV-Frontend:src/app/pages/grid-days/grid-days.component.ts",
      "name": "grid-days.component.ts",
      "qualifier": "FIL",
      "path": "src/app/pages/grid-days/grid-days.component.ts",
      "language": "ts",
      "measures": [
        {
          "metric": "comment_lines_density",
          "value": "0.0",
          "bestValue": false
        },
        { "metric": "complexity", "value": "2" },
        { "metric": "coverage", "value": "100.0", "bestValue": true },
        { "metric": "files", "value": "1" },
        { "metric": "functions", "value": "2" },
        { "metric": "ncloc", "value": "16" },
        { "metric": "security_rating", "value": "1.0", "bestValue": true },
        {
          "metric": "duplicated_lines_density",
          "value": "0.0",
          "bestValue": true
        },
        { "metric": "test_failures", "value": "0", "bestValue": true },
        { "metric": "test_errors", "value": "0", "bestValue": true }
      ]
    },
    {
      "id": "AYvsukM1bFJvH7dUSIX-",
      "key": "fga-eps-mds_2023.2-UnB-TV-Frontend:src/app/pages/grid/grid.component.css",
      "name": "grid.component.css",
      "qualifier": "FIL",
      "path": "src/app/pages/grid/grid.component.css",
      "language": "css",
      "measures": [
        {
          "metric": "comment_lines_density",
          "value": "0.0",
          "bestValue": false
        },
        { "metric": "files", "value": "1" },
        { "metric": "ncloc", "value": "20" },
        { "metric": "security_rating", "value": "1.0", "bestValue": true },
        {
          "metric": "duplicated_lines_density",
          "value": "0.0",
          "bestValue": true
        },
        { "metric": "test_failures", "value": "0", "bestValue": true },
        { "metric": "test_errors", "value": "0", "bestValue": true }
      ]
    },
    {
      "id": "AYvsukM1bFJvH7dUSIYB",
      "key": "fga-eps-mds_2023.2-UnB-TV-Frontend:src/app/pages/grid/grid.component.html",
      "name": "grid.component.html",
      "qualifier": "FIL",
      "path": "src/app/pages/grid/grid.component.html",
      "language": "web",
      "measures": [
        {
          "metric": "comment_lines_density",
          "value": "0.0",
          "bestValue": false
        },
        { "metric": "complexity", "value": "1" },
        { "metric": "files", "value": "1" },
        { "metric": "ncloc", "value": "30" },
        { "metric": "security_rating", "value": "1.0", "bestValue": true },
        {
          "metric": "duplicated_lines_density",
          "value": "0.0",
          "bestValue": true
        },
        { "metric": "test_failures", "value": "0", "bestValue": true },
        { "metric": "test_errors", "value": "0", "bestValue": true }
      ]
    },
    {
      "id": "AYvsukM1bFJvH7dUSIYA",
      "key": "fga-eps-mds_2023.2-UnB-TV-Frontend:src/app/pages/grid/grid.component.spec.ts",
      "name": "grid.component.spec.ts",
      "qualifier": "UTS",
      "path": "src/app/pages/grid/grid.component.spec.ts",
      "language": "ts",
      "measures": [
        { "metric": "security_rating", "value": "1.0", "bestValue": true },
        {
          "metric": "duplicated_lines_density",
          "value": "0.0",
          "bestValue": true
        },
        { "metric": "test_failures", "value": "0", "bestValue": true },
        { "metric": "test_errors", "value": "0", "bestValue": true }
      ]
    },
    {
      "id": "AYvsukM1bFJvH7dUSIX_",
      "key": "fga-eps-mds_2023.2-UnB-TV-Frontend:src/app/pages/grid/grid.component.ts",
      "name": "grid.component.ts",
      "qualifier": "FIL",
      "path": "src/app/pages/grid/grid.component.ts",
      "language": "ts",
      "measures": [
        {
          "metric": "comment_lines_density",
          "value": "0.0",
          "bestValue": false
        },
        { "metric": "complexity", "value": "6" },
        { "metric": "coverage", "value": "100.0", "bestValue": true },
        { "metric": "files", "value": "1" },
        { "metric": "functions", "value": "6" },
        { "metric": "ncloc", "value": "41" },
        { "metric": "security_rating", "value": "1.0", "bestValue": true },
        {
          "metric": "duplicated_lines_density",
          "value": "0.0",
          "bestValue": true
        },
        { "metric": "test_failures", "value": "0", "bestValue": true },
        { "metric": "test_errors", "value": "0", "bestValue": true }
      ]
    },
    {
      "id": "AYvsukM1bFJvH7dUSIYI",
      "key": "fga-eps-mds_2023.2-UnB-TV-Frontend:src/app/services/grid.service.spec.ts",
      "name": "grid.service.spec.ts",
      "qualifier": "UTS",
      "path": "src/app/services/grid.service.spec.ts",
      "language": "ts",
      "measures": [
        { "metric": "security_rating", "value": "1.0", "bestValue": true },
        {
          "metric": "duplicated_lines_density",
          "value": "0.0",
          "bestValue": true
        },
        { "metric": "test_failures", "value": "0", "bestValue": true },
        { "metric": "test_errors", "value": "0", "bestValue": true }
      ]
    },
    {
      "id": "AYvsukM1bFJvH7dUSIYJ",
      "key": "fga-eps-mds_2023.2-UnB-TV-Frontend:src/app/services/grid.service.ts",
      "name": "grid.service.ts",
      "qualifier": "FIL",
      "path": "src/app/services/grid.service.ts",
      "language": "ts",
      "measures": [
        {
          "metric": "comment_lines_density",
          "value": "0.0",
          "bestValue": false
        },
        { "metric": "complexity", "value": "3" },
        { "metric": "coverage", "value": "50.0", "bestValue": false },
        { "metric": "files", "value": "1" },
        { "metric": "functions", "value": "2" },
        { "metric": "ncloc", "value": "14" },
        { "metric": "security_rating", "value": "1.0", "bestValue": true },
        {
          "metric": "duplicated_lines_density",
          "value": "0.0",
          "bestValue": true
        },
        { "metric": "test_failures", "value": "0", "bestValue": true },
        { "metric": "test_errors", "value": "0", "bestValue": true }
      ]
    },
    {
      "id": "AYvaCKRBZUStRRCQ-yga",
      "key": "fga-eps-mds_2023.2-UnB-TV-Frontend:src/app/guard",
      "name": "guard",
      "qualifier": "DIR",
      "path": "src/app/guard",
      "measures": [
        {
          "metric": "comment_lines_density",
          "value": "0.0",
          "bestValue": false
        },
        { "metric": "complexity", "value": "6" },
        { "metric": "coverage", "value": "100.0", "bestValue": true },
        {
          "metric": "duplicated_lines_density",
          "value": "0.0",
          "bestValue": true
        },
        { "metric": "files", "value": "2" },
        { "metric": "functions", "value": "4" },
        { "metric": "ncloc", "value": "34" },
        { "metric": "security_rating", "value": "1.0", "bestValue": true }
      ]
    },
    {
      "id": "AYtaS0iVB6TD5Yb72jXf",
      "key": "fga-eps-mds_2023.2-UnB-TV-Frontend:src/app/helper",
      "name": "helper",
      "qualifier": "DIR",
      "path": "src/app/helper",
      "measures": [
        {
          "metric": "comment_lines_density",
          "value": "0.0",
          "bestValue": false
        },
        { "metric": "complexity", "value": "5" },
        { "metric": "coverage", "value": "84.6", "bestValue": false },
        {
          "metric": "duplicated_lines_density",
          "value": "0.0",
          "bestValue": true
        },
        { "metric": "files", "value": "1" },
        { "metric": "functions", "value": "2" },
        { "metric": "ncloc", "value": "15" },
        { "metric": "security_rating", "value": "1.0", "bestValue": true }
      ]
    },
    {
      "id": "AYvkT2yYgyiUd9TF4rBa",
      "key": "fga-eps-mds_2023.2-UnB-TV-Frontend:src/shared/model/http-error.model.ts",
      "name": "http-error.model.ts",
      "qualifier": "FIL",
      "path": "src/shared/model/http-error.model.ts",
      "language": "ts",
      "measures": [
        {
          "metric": "comment_lines_density",
          "value": "0.0",
          "bestValue": false
        },
        { "metric": "complexity", "value": "0" },
        { "metric": "files", "value": "1" },
        { "metric": "functions", "value": "0" },
        { "metric": "ncloc", "value": "3" },
        { "metric": "security_rating", "value": "1.0", "bestValue": true },
        {
          "metric": "duplicated_lines_density",
          "value": "0.0",
          "bestValue": true
        },
        { "metric": "test_failures", "value": "0", "bestValue": true },
        { "metric": "test_errors", "value": "0", "bestValue": true }
      ]
    },
    {
      "id": "AYtaa6xNgKV0OlXg3jpQ",
      "key": "fga-eps-mds_2023.2-UnB-TV-Frontend:src/shared/model/image.model.ts",
      "name": "image.model.ts",
      "qualifier": "FIL",
      "path": "src/shared/model/image.model.ts",
      "language": "ts",
      "measures": [
        {
          "metric": "comment_lines_density",
          "value": "0.0",
          "bestValue": false
        },
        { "metric": "complexity", "value": "1" },
        { "metric": "files", "value": "1" },
        { "metric": "functions", "value": "1" },
        { "metric": "ncloc", "value": "10" },
        { "metric": "security_rating", "value": "1.0", "bestValue": true },
        {
          "metric": "duplicated_lines_density",
          "value": "0.0",
          "bestValue": true
        },
        { "metric": "test_failures", "value": "0", "bestValue": true },
        { "metric": "test_errors", "value": "0", "bestValue": true }
      ]
    },
    {
      "id": "AYtaEgoHx9_KfBlJtG-a",
      "key": "fga-eps-mds_2023.2-UnB-TV-Frontend:src/index.html",
      "name": "index.html",
      "qualifier": "FIL",
      "path": "src/index.html",
      "language": "web",
      "measures": [
        {
          "metric": "comment_lines_density",
          "value": "0.0",
          "bestValue": false
        },
        { "metric": "complexity", "value": "1" },
        { "metric": "files", "value": "1" },
        { "metric": "ncloc", "value": "16" },
        { "metric": "security_rating", "value": "1.0", "bestValue": true },
        {
          "metric": "duplicated_lines_density",
          "value": "0.0",
          "bestValue": true
        },
        { "metric": "test_failures", "value": "0", "bestValue": true },
        { "metric": "test_errors", "value": "0", "bestValue": true }
      ]
    },
    {
      "id": "AYvaCKRBZUStRRCQ-ygd",
      "key": "fga-eps-mds_2023.2-UnB-TV-Frontend:src/app/interceptor",
      "name": "interceptor",
      "qualifier": "DIR",
      "path": "src/app/interceptor",
      "measures": [
        {
          "metric": "comment_lines_density",
          "value": "0.0",
          "bestValue": false
        },
        { "metric": "complexity", "value": "3" },
        { "metric": "coverage", "value": "100.0", "bestValue": true },
        {
          "metric": "duplicated_lines_density",
          "value": "0.0",
          "bestValue": true
        },
        { "metric": "files", "value": "1" },
        { "metric": "functions", "value": "1" },
        { "metric": "ncloc", "value": "24" },
        { "metric": "security_rating", "value": "1.0", "bestValue": true }
      ]
    },
    {
      "id": "AYtaEgoHx9_KfBlJtG-M",
      "key": "fga-eps-mds_2023.2-UnB-TV-Frontend:src/app/pages/login",
      "name": "login",
      "qualifier": "DIR",
      "path": "src/app/pages/login",
      "measures": [
        {
          "metric": "comment_lines_density",
          "value": "0.0",
          "bestValue": false
        },
        { "metric": "complexity", "value": "9" },
        { "metric": "coverage", "value": "100.0", "bestValue": true },
        {
          "metric": "duplicated_lines_density",
          "value": "0.0",
          "bestValue": true
        },
        { "metric": "files", "value": "3" },
        { "metric": "functions", "value": "6" },
        { "metric": "ncloc", "value": "76" },
        { "metric": "security_rating", "value": "1.0", "bestValue": true }
      ]
    },
    {
      "id": "AYtaeqq8gKV0OlXg4Ht5",
      "key": "fga-eps-mds_2023.2-UnB-TV-Frontend:src/app/pages/login-social",
      "name": "login-social",
      "qualifier": "DIR",
      "path": "src/app/pages/login-social",
      "measures": [
        {
          "metric": "comment_lines_density",
          "value": "0.0",
          "bestValue": false
        },
        { "metric": "complexity", "value": "1" },
        { "metric": "coverage", "value": "100.0", "bestValue": true },
        {
          "metric": "duplicated_lines_density",
          "value": "0.0",
          "bestValue": true
        },
        { "metric": "files", "value": "3" },
        { "metric": "functions", "value": "0" },
        { "metric": "ncloc", "value": "108" },
        { "metric": "security_rating", "value": "1.0", "bestValue": true }
      ]
    },
    {
      "id": "AYtaeqq8gKV0OlXg4Ht4",
      "key": "fga-eps-mds_2023.2-UnB-TV-Frontend:src/app/pages/login-social/login-social.component.css",
      "name": "login-social.component.css",
      "qualifier": "FIL",
      "path": "src/app/pages/login-social/login-social.component.css",
      "language": "css",
      "measures": [
        {
          "metric": "comment_lines_density",
          "value": "0.0",
          "bestValue": false
        },
        { "metric": "files", "value": "1" },
        { "metric": "ncloc", "value": "94" },
        { "metric": "security_rating", "value": "1.0", "bestValue": true },
        {
          "metric": "duplicated_lines_density",
          "value": "0.0",
          "bestValue": true
        },
        { "metric": "test_failures", "value": "0", "bestValue": true },
        { "metric": "test_errors", "value": "0", "bestValue": true }
      ]
    },
    {
      "id": "AYtaeqq8gKV0OlXg4Ht3",
      "key": "fga-eps-mds_2023.2-UnB-TV-Frontend:src/app/pages/login-social/login-social.component.html",
      "name": "login-social.component.html",
      "qualifier": "FIL",
      "path": "src/app/pages/login-social/login-social.component.html",
      "language": "web",
      "measures": [
        {
          "metric": "comment_lines_density",
          "value": "0.0",
          "bestValue": false
        },
        { "metric": "complexity", "value": "1" },
        { "metric": "files", "value": "1" },
        { "metric": "ncloc", "value": "6" },
        { "metric": "security_rating", "value": "1.0", "bestValue": true },
        {
          "metric": "duplicated_lines_density",
          "value": "0.0",
          "bestValue": true
        },
        { "metric": "test_failures", "value": "0", "bestValue": true },
        { "metric": "test_errors", "value": "0", "bestValue": true }
      ]
    },
    {
      "id": "AYtaeqq8gKV0OlXg4Ht2",
      "key": "fga-eps-mds_2023.2-UnB-TV-Frontend:src/app/pages/login-social/login-social.component.spec.ts",
      "name": "login-social.component.spec.ts",
      "qualifier": "UTS",
      "path": "src/app/pages/login-social/login-social.component.spec.ts",
      "language": "ts",
      "measures": [
        { "metric": "security_rating", "value": "1.0", "bestValue": true },
        {
          "metric": "duplicated_lines_density",
          "value": "0.0",
          "bestValue": true
        },
        { "metric": "test_failures", "value": "0", "bestValue": true },
        { "metric": "test_errors", "value": "0", "bestValue": true }
      ]
    },
    {
      "id": "AYtaeqq8gKV0OlXg4Ht1",
      "key": "fga-eps-mds_2023.2-UnB-TV-Frontend:src/app/pages/login-social/login-social.component.ts",
      "name": "login-social.component.ts",
      "qualifier": "FIL",
      "path": "src/app/pages/login-social/login-social.component.ts",
      "language": "ts",
      "measures": [
        {
          "metric": "comment_lines_density",
          "value": "0.0",
          "bestValue": false
        },
        { "metric": "complexity", "value": "0" },
        { "metric": "coverage", "value": "100.0", "bestValue": true },
        { "metric": "files", "value": "1" },
        { "metric": "functions", "value": "0" },
        { "metric": "ncloc", "value": "8" },
        { "metric": "security_rating", "value": "1.0", "bestValue": true },
        {
          "metric": "duplicated_lines_density",
          "value": "0.0",
          "bestValue": true
        },
        { "metric": "test_failures", "value": "0", "bestValue": true },
        { "metric": "test_errors", "value": "0", "bestValue": true }
      ]
    },
    {
      "id": "AYtaEgoHx9_KfBlJtG-K",
      "key": "fga-eps-mds_2023.2-UnB-TV-Frontend:src/app/pages/login/login.component.css",
      "name": "login.component.css",
      "qualifier": "FIL",
      "path": "src/app/pages/login/login.component.css",
      "language": "css",
      "measures": [
        { "metric": "files", "value": "1" },
        { "metric": "ncloc", "value": "0" },
        { "metric": "security_rating", "value": "1.0", "bestValue": true },
        {
          "metric": "duplicated_lines_density",
          "value": "0.0",
          "bestValue": true
        },
        { "metric": "test_failures", "value": "0", "bestValue": true },
        { "metric": "test_errors", "value": "0", "bestValue": true }
      ]
    },
    {
      "id": "AYtaEgoHx9_KfBlJtG-L",
      "key": "fga-eps-mds_2023.2-UnB-TV-Frontend:src/app/pages/login/login.component.html",
      "name": "login.component.html",
      "qualifier": "FIL",
      "path": "src/app/pages/login/login.component.html",
      "language": "web",
      "measures": [
        {
          "metric": "comment_lines_density",
          "value": "0.0",
          "bestValue": false
        },
        { "metric": "complexity", "value": "1" },
        { "metric": "files", "value": "1" },
        { "metric": "ncloc", "value": "22" },
        { "metric": "security_rating", "value": "1.0", "bestValue": true },
        {
          "metric": "duplicated_lines_density",
          "value": "0.0",
          "bestValue": true
        },
        { "metric": "test_failures", "value": "0", "bestValue": true },
        { "metric": "test_errors", "value": "0", "bestValue": true }
      ]
    },
    {
      "id": "AYtaEgoHx9_KfBlJtG-J",
      "key": "fga-eps-mds_2023.2-UnB-TV-Frontend:src/app/pages/login/login.component.spec.ts",
      "name": "login.component.spec.ts",
      "qualifier": "UTS",
      "path": "src/app/pages/login/login.component.spec.ts",
      "language": "ts",
      "measures": [
        { "metric": "security_rating", "value": "1.0", "bestValue": true },
        {
          "metric": "duplicated_lines_density",
          "value": "0.0",
          "bestValue": true
        },
        { "metric": "test_failures", "value": "0", "bestValue": true },
        { "metric": "test_errors", "value": "0", "bestValue": true }
      ]
    },
    {
      "id": "AYtaEgoHx9_KfBlJtG-I",
      "key": "fga-eps-mds_2023.2-UnB-TV-Frontend:src/app/pages/login/login.component.ts",
      "name": "login.component.ts",
      "qualifier": "FIL",
      "path": "src/app/pages/login/login.component.ts",
      "language": "ts",
      "measures": [
        {
          "metric": "comment_lines_density",
          "value": "0.0",
          "bestValue": false
        },
        { "metric": "complexity", "value": "8" },
        { "metric": "coverage", "value": "100.0", "bestValue": true },
        { "metric": "files", "value": "1" },
        { "metric": "functions", "value": "6" },
        { "metric": "ncloc", "value": "54" },
        { "metric": "security_rating", "value": "1.0", "bestValue": true },
        {
          "metric": "duplicated_lines_density",
          "value": "0.0",
          "bestValue": true
        },
        { "metric": "test_failures", "value": "0", "bestValue": true },
        { "metric": "test_errors", "value": "0", "bestValue": true }
      ]
    },
    {
      "id": "AYtaEgoHx9_KfBlJtG-b",
      "key": "fga-eps-mds_2023.2-UnB-TV-Frontend:src/main.ts",
      "name": "main.ts",
      "qualifier": "FIL",
      "path": "src/main.ts",
      "language": "ts",
      "measures": [
        {
          "metric": "comment_lines_density",
          "value": "0.0",
          "bestValue": false
        },
        { "metric": "complexity", "value": "1" },
        { "metric": "coverage", "value": "0.0", "bestValue": false },
        { "metric": "files", "value": "1" },
        { "metric": "functions", "value": "1" },
        { "metric": "ncloc", "value": "4" },
        { "metric": "security_rating", "value": "1.0", "bestValue": true },
        {
          "metric": "duplicated_lines_density",
          "value": "0.0",
          "bestValue": true
        },
        { "metric": "test_failures", "value": "0", "bestValue": true },
        { "metric": "test_errors", "value": "0", "bestValue": true }
      ]
    },
    {
      "id": "AYtaS0iUB6TD5Yb72jXe",
      "key": "fga-eps-mds_2023.2-UnB-TV-Frontend:src/app/helper/must-match.validator.ts",
      "name": "must-match.validator.ts",
      "qualifier": "FIL",
      "path": "src/app/helper/must-match.validator.ts",
      "language": "ts",
      "measures": [
        {
          "metric": "comment_lines_density",
          "value": "0.0",
          "bestValue": false
        },
        { "metric": "complexity", "value": "5" },
        { "metric": "coverage", "value": "84.6", "bestValue": false },
        { "metric": "files", "value": "1" },
        { "metric": "functions", "value": "2" },
        { "metric": "ncloc", "value": "15" },
        { "metric": "security_rating", "value": "1.0", "bestValue": true },
        {
          "metric": "duplicated_lines_density",
          "value": "0.0",
          "bestValue": true
        },
        { "metric": "test_failures", "value": "0", "bestValue": true },
        { "metric": "test_errors", "value": "0", "bestValue": true }
      ]
    },
    {
      "id": "AYtaEgoHx9_KfBlJtG-S",
      "key": "fga-eps-mds_2023.2-UnB-TV-Frontend:src/app/pages",
      "name": "pages",
      "qualifier": "DIR",
      "path": "src/app/pages",
      "measures": [
        {
          "metric": "comment_lines_density",
          "value": "0.0",
          "bestValue": false
        },
        { "metric": "complexity", "value": "162" },
        { "metric": "coverage", "value": "93.8", "bestValue": false },
        {
          "metric": "duplicated_lines_density",
          "value": "0.0",
          "bestValue": true
        },
        { "metric": "files", "value": "54" },
        { "metric": "functions", "value": "115" },
        { "metric": "ncloc", "value": "1533" },
        { "metric": "security_rating", "value": "1.0", "bestValue": true }
      ]
    },
    {
      "id": "AYvOSGIlPdOXal5RwOsd",
      "key": "fga-eps-mds_2023.2-UnB-TV-Frontend:src/app/pages/participate",
      "name": "participate",
      "qualifier": "DIR",
      "path": "src/app/pages/participate",
      "measures": [
        {
          "metric": "comment_lines_density",
          "value": "0.0",
          "bestValue": false
        },
        { "metric": "complexity", "value": "1" },
        { "metric": "coverage", "value": "100.0", "bestValue": true },
        {
          "metric": "duplicated_lines_density",
          "value": "0.0",
          "bestValue": true
        },
        { "metric": "files", "value": "3" },
        { "metric": "functions", "value": "0" },
        { "metric": "ncloc", "value": "43" },
        { "metric": "security_rating", "value": "1.0", "bestValue": true }
      ]
    },
    {
      "id": "AYvOSGIlPdOXal5RwOsb",
      "key": "fga-eps-mds_2023.2-UnB-TV-Frontend:src/app/pages/participate/participate.component.css",
      "name": "participate.component.css",
      "qualifier": "FIL",
      "path": "src/app/pages/participate/participate.component.css",
      "language": "css",
      "measures": [
        {
          "metric": "comment_lines_density",
          "value": "0.0",
          "bestValue": false
        },
        { "metric": "files", "value": "1" },
        { "metric": "ncloc", "value": "27" },
        { "metric": "security_rating", "value": "1.0", "bestValue": true },
        {
          "metric": "duplicated_lines_density",
          "value": "0.0",
          "bestValue": true
        },
        { "metric": "test_failures", "value": "0", "bestValue": true },
        { "metric": "test_errors", "value": "0", "bestValue": true }
      ]
    },
    {
      "id": "AYvOSGIlPdOXal5RwOsa",
      "key": "fga-eps-mds_2023.2-UnB-TV-Frontend:src/app/pages/participate/participate.component.html",
      "name": "participate.component.html",
      "qualifier": "FIL",
      "path": "src/app/pages/participate/participate.component.html",
      "language": "web",
      "measures": [
        {
          "metric": "comment_lines_density",
          "value": "0.0",
          "bestValue": false
        },
        { "metric": "complexity", "value": "1" },
        { "metric": "files", "value": "1" },
        { "metric": "ncloc", "value": "8" },
        { "metric": "security_rating", "value": "1.0", "bestValue": true },
        {
          "metric": "duplicated_lines_density",
          "value": "0.0",
          "bestValue": true
        },
        { "metric": "test_failures", "value": "0", "bestValue": true },
        { "metric": "test_errors", "value": "0", "bestValue": true }
      ]
    },
    {
      "id": "AYvOSGIlPdOXal5RwOsZ",
      "key": "fga-eps-mds_2023.2-UnB-TV-Frontend:src/app/pages/participate/participate.component.spec.ts",
      "name": "participate.component.spec.ts",
      "qualifier": "UTS",
      "path": "src/app/pages/participate/participate.component.spec.ts",
      "language": "ts",
      "measures": [
        { "metric": "security_rating", "value": "1.0", "bestValue": true },
        {
          "metric": "duplicated_lines_density",
          "value": "0.0",
          "bestValue": true
        },
        { "metric": "test_failures", "value": "0", "bestValue": true },
        { "metric": "test_errors", "value": "0", "bestValue": true }
      ]
    },
    {
      "id": "AYvOSGIlPdOXal5RwOsc",
      "key": "fga-eps-mds_2023.2-UnB-TV-Frontend:src/app/pages/participate/participate.component.ts",
      "name": "participate.component.ts",
      "qualifier": "FIL",
      "path": "src/app/pages/participate/participate.component.ts",
      "language": "ts",
      "measures": [
        {
          "metric": "comment_lines_density",
          "value": "0.0",
          "bestValue": false
        },
        { "metric": "complexity", "value": "0" },
        { "metric": "coverage", "value": "100.0", "bestValue": true },
        { "metric": "files", "value": "1" },
        { "metric": "functions", "value": "0" },
        { "metric": "ncloc", "value": "8" },
        { "metric": "security_rating", "value": "1.0", "bestValue": true },
        {
          "metric": "duplicated_lines_density",
          "value": "0.0",
          "bestValue": true
        },
        { "metric": "test_failures", "value": "0", "bestValue": true },
        { "metric": "test_errors", "value": "0", "bestValue": true }
      ]
    },
    {
      "id": "AYtaS0iUB6TD5Yb72jW9",
      "key": "fga-eps-mds_2023.2-UnB-TV-Frontend:src/app/pages/profile",
      "name": "profile",
      "qualifier": "DIR",
      "path": "src/app/pages/profile",
      "measures": [
        {
          "metric": "comment_lines_density",
          "value": "0.0",
          "bestValue": false
        },
        { "metric": "complexity", "value": "17" },
        { "metric": "coverage", "value": "78.6", "bestValue": false },
        {
          "metric": "duplicated_lines_density",
          "value": "0.0",
          "bestValue": true
        },
        { "metric": "files", "value": "3" },
        { "metric": "functions", "value": "16" },
        { "metric": "ncloc", "value": "129" },
        { "metric": "security_rating", "value": "1.0", "bestValue": true }
      ]
    },
    {
      "id": "AYtaS0iUB6TD5Yb72jW5",
      "key": "fga-eps-mds_2023.2-UnB-TV-Frontend:src/app/pages/profile/profile.component.css",
      "name": "profile.component.css",
      "qualifier": "FIL",
      "path": "src/app/pages/profile/profile.component.css",
      "language": "css",
      "measures": [
        { "metric": "files", "value": "1" },
        { "metric": "ncloc", "value": "0" },
        { "metric": "security_rating", "value": "1.0", "bestValue": true },
        {
          "metric": "duplicated_lines_density",
          "value": "0.0",
          "bestValue": true
        },
        { "metric": "test_failures", "value": "0", "bestValue": true },
        { "metric": "test_errors", "value": "0", "bestValue": true }
      ]
    },
    {
      "id": "AYtaS0iUB6TD5Yb72jW6",
      "key": "fga-eps-mds_2023.2-UnB-TV-Frontend:src/app/pages/profile/profile.component.html",
      "name": "profile.component.html",
      "qualifier": "FIL",
      "path": "src/app/pages/profile/profile.component.html",
      "language": "web",
      "measures": [
        {
          "metric": "comment_lines_density",
          "value": "0.0",
          "bestValue": false
        },
        { "metric": "complexity", "value": "1" },
        { "metric": "files", "value": "1" },
        { "metric": "ncloc", "value": "37" },
        { "metric": "security_rating", "value": "1.0", "bestValue": true },
        {
          "metric": "duplicated_lines_density",
          "value": "0.0",
          "bestValue": true
        },
        { "metric": "test_failures", "value": "0", "bestValue": true },
        { "metric": "test_errors", "value": "0", "bestValue": true }
      ]
    },
    {
      "id": "AYtaS0iUB6TD5Yb72jW7",
      "key": "fga-eps-mds_2023.2-UnB-TV-Frontend:src/app/pages/profile/profile.component.spec.ts",
      "name": "profile.component.spec.ts",
      "qualifier": "UTS",
      "path": "src/app/pages/profile/profile.component.spec.ts",
      "language": "ts",
      "measures": [
        { "metric": "security_rating", "value": "1.0", "bestValue": true },
        {
          "metric": "duplicated_lines_density",
          "value": "0.0",
          "bestValue": true
        },
        { "metric": "test_failures", "value": "0", "bestValue": true },
        { "metric": "test_errors", "value": "0", "bestValue": true }
      ]
    },
    {
      "id": "AYtaS0iUB6TD5Yb72jW8",
      "key": "fga-eps-mds_2023.2-UnB-TV-Frontend:src/app/pages/profile/profile.component.ts",
      "name": "profile.component.ts",
      "qualifier": "FIL",
      "path": "src/app/pages/profile/profile.component.ts",
      "language": "ts",
      "measures": [
        {
          "metric": "comment_lines_density",
          "value": "0.0",
          "bestValue": false
        },
        { "metric": "complexity", "value": "16" },
        { "metric": "coverage", "value": "78.6", "bestValue": false },
        { "metric": "files", "value": "1" },
        { "metric": "functions", "value": "16" },
        { "metric": "ncloc", "value": "92" },
        { "metric": "security_rating", "value": "1.0", "bestValue": true },
        {
          "metric": "duplicated_lines_density",
          "value": "0.0",
          "bestValue": true
        },
        { "metric": "test_failures", "value": "0", "bestValue": true },
        { "metric": "test_errors", "value": "0", "bestValue": true }
      ]
    },
    {
      "id": "AYvt46Php0h9nI6s-65E",
      "key": "fga-eps-mds_2023.2-UnB-TV-Frontend:src/app/pages/programacao",
      "name": "programacao",
      "qualifier": "DIR",
      "path": "src/app/pages/programacao",
      "measures": [
        {
          "metric": "comment_lines_density",
          "value": "0.0",
          "bestValue": false
        },
        { "metric": "complexity", "value": "1" },
        { "metric": "coverage", "value": "100.0", "bestValue": true },
        {
          "metric": "duplicated_lines_density",
          "value": "0.0",
          "bestValue": true
        },
        { "metric": "files", "value": "3" },
        { "metric": "functions", "value": "0" },
        { "metric": "ncloc", "value": "9" },
        { "metric": "security_rating", "value": "1.0", "bestValue": true }
      ]
    },
    {
      "id": "AYvt46Php0h9nI6s-65C",
      "key": "fga-eps-mds_2023.2-UnB-TV-Frontend:src/app/pages/programacao/programacao.component.css",
      "name": "programacao.component.css",
      "qualifier": "FIL",
      "path": "src/app/pages/programacao/programacao.component.css",
      "language": "css",
      "measures": [
        { "metric": "files", "value": "1" },
        { "metric": "ncloc", "value": "0" },
        { "metric": "security_rating", "value": "1.0", "bestValue": true },
        {
          "metric": "duplicated_lines_density",
          "value": "0.0",
          "bestValue": true
        },
        { "metric": "test_failures", "value": "0", "bestValue": true },
        { "metric": "test_errors", "value": "0", "bestValue": true }
      ]
    },
    {
      "id": "AYvt46Php0h9nI6s-65B",
      "key": "fga-eps-mds_2023.2-UnB-TV-Frontend:src/app/pages/programacao/programacao.component.html",
      "name": "programacao.component.html",
      "qualifier": "FIL",
      "path": "src/app/pages/programacao/programacao.component.html",
      "language": "web",
      "measures": [
        {
          "metric": "comment_lines_density",
          "value": "0.0",
          "bestValue": false
        },
        { "metric": "complexity", "value": "1" },
        { "metric": "files", "value": "1" },
        { "metric": "ncloc", "value": "1" },
        { "metric": "security_rating", "value": "1.0", "bestValue": true },
        {
          "metric": "duplicated_lines_density",
          "value": "0.0",
          "bestValue": true
        },
        { "metric": "test_failures", "value": "0", "bestValue": true },
        { "metric": "test_errors", "value": "0", "bestValue": true }
      ]
    },
    {
      "id": "AYvt46Php0h9nI6s-65D",
      "key": "fga-eps-mds_2023.2-UnB-TV-Frontend:src/app/pages/programacao/programacao.component.spec.ts",
      "name": "programacao.component.spec.ts",
      "qualifier": "UTS",
      "path": "src/app/pages/programacao/programacao.component.spec.ts",
      "language": "ts",
      "measures": [
        { "metric": "security_rating", "value": "1.0", "bestValue": true },
        {
          "metric": "duplicated_lines_density",
          "value": "0.0",
          "bestValue": true
        },
        { "metric": "test_failures", "value": "0", "bestValue": true },
        { "metric": "test_errors", "value": "0", "bestValue": true }
      ]
    },
    {
      "id": "AYvt46Php0h9nI6s-65A",
      "key": "fga-eps-mds_2023.2-UnB-TV-Frontend:src/app/pages/programacao/programacao.component.ts",
      "name": "programacao.component.ts",
      "qualifier": "FIL",
      "path": "src/app/pages/programacao/programacao.component.ts",
      "language": "ts",
      "measures": [
        {
          "metric": "comment_lines_density",
          "value": "0.0",
          "bestValue": false
        },
        { "metric": "complexity", "value": "0" },
        { "metric": "coverage", "value": "100.0", "bestValue": true },
        { "metric": "files", "value": "1" },
        { "metric": "functions", "value": "0" },
        { "metric": "ncloc", "value": "8" },
        { "metric": "security_rating", "value": "1.0", "bestValue": true },
        {
          "metric": "duplicated_lines_density",
          "value": "0.0",
          "bestValue": true
        },
        { "metric": "test_failures", "value": "0", "bestValue": true },
        { "metric": "test_errors", "value": "0", "bestValue": true }
      ]
    },
    {
      "id": "AYtaEgoHx9_KfBlJtG-R",
      "key": "fga-eps-mds_2023.2-UnB-TV-Frontend:src/app/pages/register",
      "name": "register",
      "qualifier": "DIR",
      "path": "src/app/pages/register",
      "measures": [
        {
          "metric": "comment_lines_density",
          "value": "0.0",
          "bestValue": false
        },
        { "metric": "complexity", "value": "12" },
        { "metric": "coverage", "value": "95.8", "bestValue": false },
        {
          "metric": "duplicated_lines_density",
          "value": "0.0",
          "bestValue": true
        },
        { "metric": "files", "value": "3" },
        { "metric": "functions", "value": "10" },
        { "metric": "ncloc", "value": "105" },
        { "metric": "security_rating", "value": "1.0", "bestValue": true }
      ]
    },
    {
      "id": "AYtaEgoHx9_KfBlJtG-Q",
      "key": "fga-eps-mds_2023.2-UnB-TV-Frontend:src/app/pages/register/register.component.css",
      "name": "register.component.css",
      "qualifier": "FIL",
      "path": "src/app/pages/register/register.component.css",
      "language": "css",
      "measures": [
        { "metric": "files", "value": "1" },
        { "metric": "ncloc", "value": "0" },
        { "metric": "security_rating", "value": "1.0", "bestValue": true },
        {
          "metric": "duplicated_lines_density",
          "value": "0.0",
          "bestValue": true
        },
        { "metric": "test_failures", "value": "0", "bestValue": true },
        { "metric": "test_errors", "value": "0", "bestValue": true }
      ]
    },
    {
      "id": "AYtaEgoHx9_KfBlJtG-O",
      "key": "fga-eps-mds_2023.2-UnB-TV-Frontend:src/app/pages/register/register.component.html",
      "name": "register.component.html",
      "qualifier": "FIL",
      "path": "src/app/pages/register/register.component.html",
      "language": "web",
      "measures": [
        {
          "metric": "comment_lines_density",
          "value": "0.0",
          "bestValue": false
        },
        { "metric": "complexity", "value": "1" },
        { "metric": "files", "value": "1" },
        { "metric": "ncloc", "value": "24" },
        { "metric": "security_rating", "value": "1.0", "bestValue": true },
        {
          "metric": "duplicated_lines_density",
          "value": "0.0",
          "bestValue": true
        },
        { "metric": "test_failures", "value": "0", "bestValue": true },
        { "metric": "test_errors", "value": "0", "bestValue": true }
      ]
    },
    {
      "id": "AYtaEgoHx9_KfBlJtG-N",
      "key": "fga-eps-mds_2023.2-UnB-TV-Frontend:src/app/pages/register/register.component.spec.ts",
      "name": "register.component.spec.ts",
      "qualifier": "UTS",
      "path": "src/app/pages/register/register.component.spec.ts",
      "language": "ts",
      "measures": [
        { "metric": "security_rating", "value": "1.0", "bestValue": true },
        {
          "metric": "duplicated_lines_density",
          "value": "0.0",
          "bestValue": true
        },
        { "metric": "test_failures", "value": "0", "bestValue": true },
        { "metric": "test_errors", "value": "0", "bestValue": true }
      ]
    },
    {
      "id": "AYtaEgoHx9_KfBlJtG-P",
      "key": "fga-eps-mds_2023.2-UnB-TV-Frontend:src/app/pages/register/register.component.ts",
      "name": "register.component.ts",
      "qualifier": "FIL",
      "path": "src/app/pages/register/register.component.ts",
      "language": "ts",
      "measures": [
        {
          "metric": "comment_lines_density",
          "value": "0.0",
          "bestValue": false
        },
        { "metric": "complexity", "value": "11" },
        { "metric": "coverage", "value": "95.8", "bestValue": false },
        { "metric": "files", "value": "1" },
        { "metric": "functions", "value": "10" },
        { "metric": "ncloc", "value": "81" },
        { "metric": "security_rating", "value": "1.0", "bestValue": true },
        {
          "metric": "duplicated_lines_density",
          "value": "0.0",
          "bestValue": true
        },
        { "metric": "test_failures", "value": "0", "bestValue": true },
        { "metric": "test_errors", "value": "0", "bestValue": true }
      ]
    },
    {
      "id": "AYtaS0iUB6TD5Yb72jXH",
      "key": "fga-eps-mds_2023.2-UnB-TV-Frontend:src/app/pages/reset-password",
      "name": "reset-password",
      "qualifier": "DIR",
      "path": "src/app/pages/reset-password",
      "measures": [
        {
          "metric": "comment_lines_density",
          "value": "0.0",
          "bestValue": false
        },
        { "metric": "complexity", "value": "8" },
        { "metric": "coverage", "value": "100.0", "bestValue": true },
        {
          "metric": "duplicated_lines_density",
          "value": "0.0",
          "bestValue": true
        },
        { "metric": "files", "value": "3" },
        { "metric": "functions", "value": "6" },
        { "metric": "ncloc", "value": "68" },
        { "metric": "security_rating", "value": "1.0", "bestValue": true }
      ]
    }
  ]
}
